crumbs/__init__.py
crumbs/information.py
crumbs-2.1.0.data/data/share/doc/crumbs-2.1.0/README.rst
crumbs-2.1.0.dist-info/DESCRIPTION.rst
crumbs-2.1.0.dist-info/METADATA
crumbs-2.1.0.dist-info/RECORD
crumbs-2.1.0.dist-info/WHEEL
crumbs-2.1.0.dist-info/metadata.json
crumbs-2.1.0.dist-info/pbr.json
crumbs-2.1.0.dist-info/top_level.txt
