Metadata-Version: 2.0
Name: crumbs
Version: 2.1.0
Summary: Generalized all-in-one parameters module.
Home-page: https://github.com/alunduil/crumbs
Author: Alex Brandt
Author-email: alunduil@alunduil.com
License: MIT
Keywords: crumbs,parameters,configuration,environment,arguments
Platform: UNKNOWN
Classifier: Development Status :: 5 - Production/Stable
Classifier: Intended Audience :: Developers
Classifier: License :: OSI Approved :: MIT License
Classifier: Natural Language :: English
Classifier: Operating System :: OS Independent
Classifier: Programming Language :: Python
Classifier: Programming Language :: Python :: 2
Classifier: Programming Language :: Python :: 2.6
Classifier: Programming Language :: Python :: 2.7
Classifier: Programming Language :: Python :: 3
Classifier: Programming Language :: Python :: 3.3
Classifier: Programming Language :: Python :: 3.4
Classifier: Programming Language :: Python :: 3.5
Classifier: Programming Language :: Python :: Implementation :: CPython
Classifier: Topic :: Software Development :: Libraries
Provides-Extra: inotify
Requires-Dist: pyinotify; extra == 'inotify'
